sanic_dantic/__init__.py
sanic_dantic/basic_definition.py
sanic_dantic/sanic_class_dantic.py
sanic_dantic/sanic_function_dantic.py
sanic_dantic-1.2.2.dist-info/LICENSE
sanic_dantic-1.2.2.dist-info/METADATA
sanic_dantic-1.2.2.dist-info/WHEEL
sanic_dantic-1.2.2.dist-info/top_level.txt
sanic_dantic-1.2.2.dist-info/RECORD
