Metadata-Version: 2.1
Name: sanic-dantic
Version: 1.2.2
Summary: A request parameter checking and parsing library
Home-page: https://github.com/misss85246/sanic-dantic
Author: Connor Zhang
Author-email: chzhangyue@outlook.com
Classifier: Programming Language :: Python :: 3.8
Classifier: Programming Language :: Python :: 3.9
Classifier: Programming Language :: Python :: 3.10
Classifier: Topic :: Utilities
Classifier: Environment :: Web Environment
Classifier: Intended Audience :: Developers
Classifier: Operating System :: OS Independent
Classifier: License :: OSI Approved :: MIT License
Requires-Python: >=3.8
License-File: LICENSE
Requires-Dist: pydantic (>=1.10.2)
Requires-Dist: sanic (>=21.3.4)
